sap/__init__.py
sap/exceptions.py
sap/loggers.py
sap/py.typed
sap/settings.py
sap/beanie/__init__.py
sap/beanie/client.py
sap/beanie/document.py
sap/beanie/link.py
sap/beanie/mixins.py
sap/beanie/patch.py
sap/beanie/query.py
sap/chart/__init__.py
sap/chart/serializers.py
sap/fastapi/__init__.py
sap/fastapi/auth.py
sap/fastapi/cache.py
sap/fastapi/forms.py
sap/fastapi/middleware.py
sap/fastapi/pagination.py
sap/fastapi/serializers.py
sap/fastapi/user.py
sap/fastapi/utils.py
sap/pydantic/__init__.py
sap/rest/__init__.py
sap/rest/client.py
sap/rest/rest_exceptions.py
sap/sqlachemy/__init__.py
sap/tests/__init__.py
sap/tests/apm_pymongo.py
sap/tests/crons.py
sap/tests/rest.py
sap/tests/utils.py
sap/typing/__init__.py
sap/worker/__init__.py
sap/worker/amqp.py
sap/worker/config.py
sap/worker/crons.py
sap/worker/crons_airtable.py
sap/worker/debug.py
sap/worker/exceptions.py
sap/worker/lambdas.py
sap/worker/packet.py
sap/worker/utils.py
sapx-0.4.5.dist-info/METADATA
sapx-0.4.5.dist-info/WHEEL
sapx-0.4.5.dist-info/top_level.txt
sapx-0.4.5.dist-info/RECORD
